loggendra_server/__init__.py
loggendra_server-0.0.1.dist-info/METADATA
loggendra_server-0.0.1.dist-info/RECORD
loggendra_server-0.0.1.dist-info/WHEEL
loggendra_server-0.0.1.dist-info/top_level.txt
